websuckets/__init__.py
websuckets/cache.py
websuckets/encoders.py
websuckets/exc.py
websuckets/interfaces.py
websuckets/io.py
websuckets/models.py
websuckets/security.py
websuckets/session.py
websuckets/types.py
websuckets/websuckets.py
websuckets-0.0.1.dev1.dist-info/METADATA
websuckets-0.0.1.dev1.dist-info/WHEEL
websuckets-0.0.1.dev1.dist-info/top_level.txt
websuckets-0.0.1.dev1.dist-info/RECORD
